
{
  "A&E": "https://epg.pw/api/epg.json?channel_id=523311",
  "Adult Swim HD": "https://epg.pw/api/epg.json?channel_id=417185",
  "AMC": "https://epg.pw/api/epg.json?channel_id=523312",
  "Animal Planet": "https://epg.pw/api/epg.json?channel_id=523297",
  "Arte 1": "https://epg.pw/api/epg.json?channel_id=523338",
  "AXN": "https://epg.pw/api/epg.json?channel_id=523313",
  "Baby TV": "https://epg.pw/api/epg.json?channel_id=523317",
  "Band RJ": "https://epg.pw/api/epg.json?channel_id=523315",
  "Band News": "https://epg.pw/api/epg.json?channel_id=523314",
  "Band Sports": "https://epg.pw/api/epg.json?channel_id=523330",
  "BBC World News": "https://epg.pw/api/epg.json?channel_id=523303",
  "Bis": "https://epg.pw/api/epg.json?channel_id=523324",
  "Bloomberg": "https://epg.pw/api/epg.json?channel_id=523296",
  "Canal 21": "https://epg.pw/api/epg.json?channel_id=523327",
  "Canal Brasil": "https://epg.pw/api/epg.json?channel_id=523319",
  "Canal do Boi": "https://epg.pw/api/epg.json?channel_id=523289",
  "Canal Rural": "https://epg.pw/api/epg.json?channel_id=523340",
  "Cartoon Network": "https://epg.pw/api/epg.json?channel_id=523325",
  "Cinemax": "https://epg.pw/api/epg.json?channel_id=523277",
  "CNN Brasil": "https://epg.pw/api/epg.json?channel_id=426108",
  "CNN International": "https://epg.pw/api/epg.json?channel_id=523278",
  "Combate": "https://epg.pw/api/epg.json?channel_id=523284",
  "Comedy Central": "https://epg.pw/api/epg.json?channel_id=523280",
  "Deutsche Welle": "https://epg.pw/api/epg.json?channel_id=523268",
  "Discovery Channel": "https://epg.pw/api/epg.json?channel_id=523309",
  "Discovery HD Theater": "https://epg.pw/api/epg.json?channel_id=523292",
  "Discovery H&H": "https://epg.pw/api/epg.json?channel_id=523310",
  "Discovery ID": "https://raw.githubusercontent.com/AgronBellum/test_cachorro/refs/heads/main/ID_BR.json",
  "Discovery Home and Health HD": "https://epg.pw/api/epg.json?channel_id=435551",
  "Discovery Kids": "https://epg.pw/api/epg.json?channel_id=523318",
  "Discovery Science": "https://epg.pw/api/epg.json?channel_id=523359",
  "Discovery Turbo": "https://epg.pw/api/epg.json?channel_id=523326",
  "Discovery World": "https://epg.pw/api/epg.json?channel_id=523272",
  "E! Entertainment Television": "https://epg.pw/api/epg.json?channel_id=523283",
  "ESPN": "https://epg.pw/api/epg.json?channel_id=418725",
  "ESPN 2": "https://epg.pw/api/epg.json?channel_id=418722",
  "ESPN 3": "https://epg.pw/api/epg.json?channel_id=523329",
  "ESPN 4": "https://epg.pw/api/epg.json?channel_id=523357",
  "ESPN 5": "https://epg.pw/api/epg.json?channel_id=418724",
  "ESPN 6": "https://epg.pw/api/epg.json?channel_id=417391",
  "Eurochannel": "https://epg.pw/api/epg.json?channel_id=523287",
  "Film & Arts": "https://epg.pw/api/epg.json?channel_id=523354",
  "FRANCE 24 HD": "https://epg.pw/api/epg.json?channel_id=417386",
  "Futura": "https://epg.pw/api/epg.json?channel_id=523343",
  "Globo": "https://epg.pw/api/epg.json?channel_id=523353",
  "Globo RJ": "https://epg.pw/api/epg.json?channel_id=523353",
  "Globo RS":"https://raw.githubusercontent.com/AgronBellum/test_cachorro/refs/heads/main/RS_BR.json",
  "Globo News": "https://epg.pw/api/epg.json?channel_id=523341",
  "Gloob": "https://epg.pw/api/epg.json?channel_id=523336",
  "GNT": "https://epg.pw/api/epg.json?channel_id=523276",
  "HBO": "https://epg.pw/api/epg.json?channel_id=417383",
  "HBO 2": "https://epg.pw/api/epg.json?channel_id=523348",
  "HBO Family": "https://epg.pw/api/epg.json?channel_id=523290",
  "HBO Plus": "https://epg.pw/api/epg.json?channel_id=523328",
  "HBO Signature": "https://epg.pw/api/epg.json?channel_id=523274",
  "HBO+": "https://epg.pw/api/epg.json?channel_id=418723",
  "History Channel": "https://epg.pw/api/epg.json?channel_id=523342",
  "Jovem Pan News": "https://epg.pw/api/epg.json?channel_id=417187",
  "Lifetime": "https://epg.pw/api/epg.json?channel_id=523356",
  "Megapix": "https://epg.pw/api/epg.json?channel_id=523293",
  "MTV": "https://epg.pw/api/epg.json?channel_id=523308",
  "Multishow": "https://epg.pw/api/epg.json?channel_id=523321",
  "Nick Jr.": "https://epg.pw/api/epg.json?channel_id=523322",
  "Nickelodeon": "https://epg.pw/api/epg.json?channel_id=523299",
  "OFF HD": "https://epg.pw/api/epg.json?channel_id=523285",
  "Paramount Channel": "https://epg.pw/api/epg.json?channel_id=523275",
  "Premiere 1": "https://epg.pw/api/epg.json?channel_id=523267",
  "Premiere 2": "https://epg.pw/api/epg.json?lang=en&date=20260426&channel_id=425970",
  "Premiere 3": "https://epg.pw/api/epg.json?channel_id=425997",
  "RAI International": "https://epg.pw/api/epg.json?channel_id=523304",
  "Record News": "https://epg.pw/api/epg.json?channel_id=523352",
  "Record RJ": "https://epg.pw/api/epg.json?channel_id=523282",
  "Record SP": "https://epg.pw/api/epg.json?channel_id=426071",
  "Rede Boa Vontade": "https://epg.pw/api/epg.json?channel_id=523323",
  "Rede Brasil HD": "https://epg.pw/api/epg.json?channel_id=417589",
  "Rede TV": "https://epg.pw/api/epg.json?channel_id=523301",
  "Rede Vida": "https://epg.pw/api/epg.json?channel_id=523337",
  "Sabor & Arte": "https://epg.pw/api/epg.json?channel_id=417387",
  "SBT": "https://epg.pw/api/epg.json?channel_id=523298",
  "SIC International": "https://epg.pw/api/epg.json?channel_id=523334",
  "Sony": "https://epg.pw/api/epg.json?channel_id=523333",
  "Sony Movies Brazil": "https://epg.pw/api/epg.json?channel_id=417588",
  "SPACE": "https://epg.pw/api/epg.json?channel_id=523347",
  "SporTV": "https://epg.pw/api/epg.json?channel_id=523358",
  "SporTV 2": "https://epg.pw/api/epg.json?channel_id=523271",
  "SporTV 3": "https://epg.pw/api/epg.json?channel_id=523269",
  "Studio Universal": "https://epg.pw/api/epg.json?channel_id=523320",
  "TBS": "https://epg.pw/api/epg.json?channel_id=523344",
  "TCM - Turner Classic": "https://epg.pw/api/epg.json?channel_id=523316",
  "Telecine Action": "https://epg.pw/api/epg.json?channel_id=523346",
  "Telecine Cult": "https://epg.pw/api/epg.json?channel_id=523286",
  "Telecine Fun": "https://epg.pw/api/epg.json?channel_id=523288",
  "Telecine Pipoca": "https://epg.pw/api/epg.json?channel_id=523291",
  "Telecine Premium": "https://epg.pw/api/epg.json?channel_id=523351",
  "Telecine Touch": "https://epg.pw/api/epg.json?channel_id=523306",
  "TLC": "https://epg.pw/api/epg.json?channel_id=523307",
  "TNT": "https://epg.pw/api/epg.json?channel_id=523279",
  "TNT Séries": "https://epg.pw/api/epg.json?channel_id=523294",
  "Tooncast": "https://epg.pw/api/epg.json?channel_id=523281",
  "Travel Box Brazil": "https://epg.pw/api/epg.json?channel_id=523331",
  "TV Aparecida (aberta)": "https://epg.pw/api/epg.json?channel_id=523345",
  "TV Brasil": "https://epg.pw/api/epg.json?channel_id=523339",
  "TV Cultura": "https://epg.pw/api/epg.json?channel_id=523305",
  "TV Escola": "https://epg.pw/api/epg.json?channel_id=523295",
  "TV Espanha": "https://epg.pw/api/epg.json?channel_id=523332",
  "TV Gazeta": "https://epg.pw/api/epg.json?channel_id=523302",
  "TV Justiça": "https://epg.pw/api/epg.json?channel_id=523355",
  "TV Senado": "https://epg.pw/api/epg.json?channel_id=523335",
  "TV5 Monde": "https://epg.pw/api/epg.json?channel_id=523300",
  "Universal Channel": "https://epg.pw/api/epg.json?channel_id=523349",
  "Viva": "https://epg.pw/api/epg.json?channel_id=523270",
  "Warner Channel": "https://epg.pw/api/epg.json?channel_id=523350",
  "Woohoo": "https://epg.pw/api/epg.json?channel_id=523273"
}
